wikidata_plain_sparql/__init__.py
wikidata_plain_sparql-0.0.6.dist-info/LICENSE
wikidata_plain_sparql-0.0.6.dist-info/METADATA
wikidata_plain_sparql-0.0.6.dist-info/WHEEL
wikidata_plain_sparql-0.0.6.dist-info/top_level.txt
wikidata_plain_sparql-0.0.6.dist-info/RECORD
