Metadata-Version: 2.1
Name: wikidata-plain-sparql
Version: 0.0.6
Summary: Query WikiData in plain SPARQL and display the result as a map or data frame
Home-page: https://github.com/jelleschutter/wikidata-plain-sparql
Author: Jelle Schutter
Author-email: jelle@schutter.xyz
License: UNKNOWN
Platform: UNKNOWN
Classifier: Programming Language :: Python :: 3
Classifier: License :: OSI Approved :: MIT License
Classifier: Operating System :: OS Independent
Requires-Dist: pandas
Requires-Dist: requests
Requires-Dist: bokeh
